MANIFEST.in
README.md
setup.py
config/mcrunner.sample.conf
mcrunner/__init__.py
mcrunner/connection.py
mcrunner/daemon.py
mcrunner/exceptions.py
mcrunner/mcrunner.py
mcrunner/mcrunnerd.py
mcrunner/plugin_change.py
mcrunner/server.py
mcrunner/server_status.py
mcrunner.egg-info/PKG-INFO
mcrunner.egg-info/SOURCES.txt
mcrunner.egg-info/dependency_links.txt
mcrunner.egg-info/entry_points.txt
mcrunner.egg-info/pbr.json
mcrunner.egg-info/requires.txt
mcrunner.egg-info/top_level.txt
mcrunner/tests/__init__.py
mcrunner/tests/test_connection.py
mcrunner/tests/test_mcrunner.py
mcrunner/tests/test_mcrunnerd.py
mcrunner/tests/test_plugin_change.py
mcrunner/tests/test_server.py