Metadata-Version: 1.1
Name: mcrunner
Version: 0.1.4
Summary: Minecraft server monitoring and control system for UNIX
Home-page: https://github.com/sbezboro/mcrunner
Author: Sergei Bezborodko
Author-email: sergei.b.ru@gmail.com
License: MIT
Keywords: minecraft server runner
Platform: UNKNOWN
Classifier: License :: OSI Approved :: MIT License
Classifier: Programming Language :: Python :: 2
Classifier: Programming Language :: Python :: 2.6
Classifier: Programming Language :: Python :: 2.7
Classifier: Programming Language :: Python :: 3
Classifier: Programming Language :: Python :: 3.3
Classifier: Programming Language :: Python :: 3.4
